minimol/__init__.py
minimol/model.py
minimol/ckpts/__init__.py
minimol/ckpts/minimol_v1/__init__.py
minimol/ckpts/minimol_v1/base_shape.yaml
minimol/ckpts/minimol_v1/config.yaml
minimol/ckpts/minimol_v1/state_dict.pth
minimol-1.3.4.dist-info/LICENSE
minimol-1.3.4.dist-info/METADATA
minimol-1.3.4.dist-info/WHEEL
minimol-1.3.4.dist-info/top_level.txt
minimol-1.3.4.dist-info/RECORD
