Metadata-Version: 2.1
Name: minimol
Version: 1.3.4
Summary: Molecular fingerprinting using pre-trained deep nets
Home-page: https://github.com/graphcore-research/minimol
Author: Blazej Banaszewski, Kerstin Klaser
Author-email: blazej@banaszewski.pl, kerstink@graphcore.ai
Requires-Python: >=3.9
License-File: LICENSE
Requires-Dist: graphium ==2.4.7
Requires-Dist: hydra-core
